donnes_des_sous_theo/__init__.py
donnes_des_sous_theo/banque.py
donnes_des_sous_theo-0.1.1.dist-info/WHEEL
donnes_des_sous_theo-0.1.1.dist-info/entry_points.txt
donnes_des_sous_theo-0.1.1.dist-info/METADATA
donnes_des_sous_theo-0.1.1.dist-info/RECORD
