Metadata-Version: 2.3
Name: donnes-des-sous-theo
Version: 0.1.1
Summary: Add your description here
Author: theoc
Author-email: theoc <theo.colin@ig2i.centralelille.fr>
Requires-Dist: httpx>=0.28.1
Requires-Python: >=3.13
